{
	"configurations" : 
	[
		{
			"directories" : 
			[
				{
					"build" : ".",
					"jsonFile" : "directory-.-Debug-f5ebdc15457944623624.json",
					"minimumCMakeVersion" : 
					{
						"string" : "3.25"
					},
					"projectIndex" : 0,
					"source" : ".",
					"targetIndexes" : 
					[
						0
					]
				}
			],
			"name" : "Debug",
			"projects" : 
			[
				{
					"directoryIndexes" : 
					[
						0
					],
					"name" : "be_pam",
					"targetIndexes" : 
					[
						0
					]
				}
			],
			"targets" : 
			[
				{
					"directoryIndex" : 0,
					"id" : "be_pam::@6890427a1f51a3e7e1df",
					"jsonFile" : "target-be_pam-Debug-ddc3f368cc2b1170c82a.json",
					"name" : "be_pam",
					"projectIndex" : 0
				}
			]
		}
	],
	"kind" : "codemodel",
	"paths" : 
	{
		"build" : "/tmp/tmp.fXBcTgLLmY/cmake-build-debug-remote",
		"source" : "/tmp/tmp.fXBcTgLLmY"
	},
	"version" : 
	{
		"major" : 2,
		"minor" : 4
	}
}
